{
  "schema_version": "1.0",
  "template": "system_base.md",
  "entries": [
    {
      "entry_id": "E001",
      "semantic_id": "system_base.global_system_rules",
      "source_path": "resources/prompt_blocks/phase/system_base/global_system_rules.md",
      "source_prompt_span": {
        "line_start": 1,
        "line_end": 30
      },
      "owner_phase": "system",
      "applies_to": [
        "system_base.md"
      ],
      "guard_level": "guarded",
      "risk_class": "critical",
      "dedupe_eligible": false,
      "repeat_policy": {
        "repeat_count": 1
      }
    }
  ]
}
